{
  "fluentMethods": true,
  "clientRootFolder": "",
  "relationships": [],
  "fields": [
    {
      "fieldName": "contactName",
      "fieldType": "String"
    },
    {
      "fieldName": "department",
      "fieldType": "String"
    },
    {
      "fieldName": "telephoneExtension",
      "fieldType": "String"
    },
    {
      "fieldName": "phoneNumber",
      "fieldType": "String"
    }
  ],
  "changelogDate": "20200809141735",
  "dto": "mapstruct",
  "searchEngine": "elasticsearch",
  "service": "serviceImpl",
  "entityTableName": "contact",
  "databaseType": "sql",
  "readOnly": false,
  "jpaMetamodelFiltering": true,
  "pagination": "pagination"
}
